diagnostic_tool/__init__.py
diagnostic_tool/collector.py
diagnostic_tool/conf_validator.py
diagnostic_tool/connector.py
diagnostic_tool/diagnose.py
diagnostic_tool/dist_conf.py
diagnostic_tool/inspect.py
diagnostic_tool/log_analyzer.py
diagnostic_tool/parser.py
diagnostic_tool/pb.py
diagnostic_tool/rpc.py
diagnostic_tool/server_checker.py
diagnostic_tool/table_checker.py
diagnostic_tool/util.py
openmldb_tool-0.9.2.dist-info/METADATA
openmldb_tool-0.9.2.dist-info/WHEEL
openmldb_tool-0.9.2.dist-info/entry_points.txt
openmldb_tool-0.9.2.dist-info/top_level.txt
openmldb_tool-0.9.2.dist-info/RECORD
