Metadata-Version: 2.1
Name: openmldb-tool
Version: 0.9.2
Summary: OpenMLDB Tool
Home-page: https://github.com/4paradigm/OpenMLDB
Author: OpenMLDB Team
Author-email: 
License: copyright 4paradigm.com
Platform: UNKNOWN
Classifier: Programming Language :: Python :: 3
Requires-Dist: openmldb (>=0.8.1)
Requires-Dist: absl-py
Requires-Dist: pyyaml
Requires-Dist: paramiko
Requires-Dist: termplotlib
Requires-Dist: requests
Provides-Extra: pb
Requires-Dist: protobuf (==3.6.1) ; extra == 'pb'
Requires-Dist: beautifulsoup4 ; extra == 'pb'
Provides-Extra: test
Requires-Dist: openmldb-tool[pb] ; extra == 'test'
Requires-Dist: pytest ; extra == 'test'
